setup.py
paper2tmb/__init__.py
paper2tmb/main.py
paper2tmb/manipulator.py
paper2tmb.egg-info/PKG-INFO
paper2tmb.egg-info/SOURCES.txt
paper2tmb.egg-info/dependency_links.txt
paper2tmb.egg-info/entry_points.txt
paper2tmb.egg-info/requires.txt
paper2tmb.egg-info/top_level.txt