Metadata-Version: 1.1
Name: paper2tmb
Version: 0.0.1
Summary: Convert academic papers (pdf) to nice tmb (png)
Home-page: https://github.com/sotetsuk/paper2tmb
Author: sotetsuk
Author-email: sotetsu.koyamada@gmail.com
License: MIT
Platform: UNKNOWN
Classifier: Programming Language :: Python :: 3.3
Classifier: Programming Language :: Python :: 3.4
Classifier: Programming Language :: Python :: 3.5
Classifier: License :: OSI Approved :: MIT License
